[
{ "recipient": "", "amount": , "lockBlocks":0, "vestingBlocks":2592000 },
{ "recipient": "", "amount": , "lockBlocks":0, "vestingBlocks":2592000 },
{ "recipient": "", "amount": , "lockBlocks":0, "vestingBlocks":2592000 },
{ "recipient": "", "amount": , "lockBlocks":0, "vestingBlocks":2592000 },
{ "recipient": "", "amount": , "lockBlocks":0, "vestingBlocks":2592000 },
{ "recipient": "", "amount": , "lockBlocks":0, "vestingBlocks":2592000 },
{ "recipient": "", "amount": , "lockBlocks":0, "vestingBlocks":2592000 },
{ "recipient": "", "amount": , "lockBlocks":0, "vestingBlocks":2592000 },
{ "recipient": "", "amount": , "lockBlocks":0, "vestingBlocks":2592000 },
{ "recipient": "", "amount": , "lockBlocks":0, "vestingBlocks":2592000 },
{ "recipient": "", "amount": , "lockBlocks":0, "vestingBlocks":2592000 },
{ "recipient": "", "amount": , "lockBlocks":0, "vestingBlocks":2592000 },
{ "recipient": "", "amount": , "lockBlocks":0, "vestingBlocks":2592000 },
]
